{
  "label": "gMetaSprite_omega_zx_omega_zx",
  "data": [
    {
      "sheetIdx": 0,
      "subsprites": [
        {
          "tileNum": 180,
          "xflip": false,
          "yflip": false,
          "size": [
            8,
            16
          ],
          "x": 40,
          "y": -7
        },
        {
          "tileNum": 160,
          "xflip": false,
          "yflip": false,
          "size": [
            16,
            32
          ],
          "x": 40,
          "y": 9
        },
        {
          "tileNum": 64,
          "xflip": false,
          "yflip": false,
          "size": [
            32,
            64
          ],
          "x": 8,
          "y": -11
        }
      ]
    },
    {
      "sheetIdx": 0,
      "subsprites": [
        {
          "tileNum": 188,
          "xflip": false,
          "yflip": false,
          "size": [
            8,
            8
          ],
          "x": 20,
          "y": 4
        },
        {
          "tileNum": 152,
          "xflip": false,
          "yflip": false,
          "size": [
            32,
            16
          ],
          "x": 20,
          "y": -12
        },
        {
          "tileNum": 0,
          "xflip": false,
          "yflip": false,
          "size": [
            64,
            64
          ],
          "x": 4,
          "y": -76
        },
        {
          "tileNum": 128,
          "xflip": false,
          "yflip": false,
          "size": [
            16,
            32
          ],
          "x": 68,
          "y": -29
        },
        {
          "tileNum": 172,
          "xflip": false,
          "yflip": false,
          "size": [
            16,
            16
          ],
          "x": 52,
          "y": -12
        }
      ]
    },
    {
      "sheetIdx": 0,
      "subsprites": [
        {
          "tileNum": 184,
          "xflip": false,
          "yflip": false,
          "size": [
            16,
            8
          ],
          "x": 44,
          "y": 36
        },
        {
          "tileNum": 136,
          "xflip": false,
          "yflip": false,
          "size": [
            16,
            32
          ],
          "x": 44,
          "y": 4
        },
        {
          "tileNum": 144,
          "xflip": false,
          "yflip": false,
          "size": [
            16,
            32
          ],
          "x": 44,
          "y": -28
        },
        {
          "tileNum": 96,
          "xflip": false,
          "yflip": false,
          "size": [
            32,
            64
          ],
          "x": 12,
          "y": -24
        }
      ]
    },
    {
      "sheetIdx": 0,
      "subsprites": [
        {
          "tileNum": 182,
          "xflip": false,
          "yflip": false,
          "size": [
            8,
            16
          ],
          "x": 14,
          "y": 16
        },
        {
          "tileNum": 168,
          "xflip": false,
          "yflip": false,
          "size": [
            8,
            32
          ],
          "x": 14,
          "y": -16
        },
        {
          "tileNum": 184,
          "xflip": false,
          "yflip": false,
          "size": [
            16,
            8
          ],
          "x": 44,
          "y": 36
        },
        {
          "tileNum": 136,
          "xflip": false,
          "yflip": false,
          "size": [
            16,
            32
          ],
          "x": 44,
          "y": 4
        },
        {
          "tileNum": 144,
          "xflip": false,
          "yflip": false,
          "size": [
            16,
            32
          ],
          "x": 44,
          "y": -28
        },
        {
          "tileNum": 96,
          "xflip": false,
          "yflip": false,
          "size": [
            32,
            64
          ],
          "x": 12,
          "y": -24
        }
      ]
    },
    {
      "sheetIdx": 0,
      "subsprites": [
        {
          "tileNum": 186,
          "xflip": false,
          "yflip": false,
          "size": [
            8,
            16
          ],
          "x": 18,
          "y": 16
        },
        {
          "tileNum": 176,
          "xflip": false,
          "yflip": false,
          "size": [
            8,
            32
          ],
          "x": 18,
          "y": -16
        }
      ]
    }
  ]
}